pazgas_power/__init__.py
pazgas_power/api.py
pazgas_power/auth_api.py
pazgas_power/commons.py
pazgas_power/const.py
pazgas_power/exceptions.py
pazgas_power/models/auth.py
pazgas_power/models/common.py
pazgas_power/models/customer_data.py
pazgas_power/models/error.py
pazgas_power/models/package.py
pazgas_power-0.0.5.dist-info/LICENSE
pazgas_power-0.0.5.dist-info/METADATA
pazgas_power-0.0.5.dist-info/WHEEL
pazgas_power-0.0.5.dist-info/RECORD
