Metadata-Version: 2.1
Name: pazgas-power
Version: 0.0.5
Summary: A python wrapper for PazGas Power
License: MIT
Author: Guy Khmelnitsky
Author-email: guykhmel@gmail.com
Requires-Python: >=3.11,<4.0
Classifier: License :: OSI Approved :: MIT License
Classifier: Programming Language :: Python :: 3
Classifier: Programming Language :: Python :: 3.11
Classifier: Programming Language :: Python :: 3.12
Requires-Dist: aiofiles (>=24.1.0,<25.0.0)
Requires-Dist: aiohttp (>=3.9.5,<4.0.0)
Requires-Dist: mashumaro (>=3.13.1,<4.0.0)
